imgpro/__init__.py
imgpro/processing/__init__.py
imgpro/processing/combination.py
imgpro/processing/transformation.py
imgpro/utils/__init__.py
imgpro/utils/io.py
imgpro/utils/plot.py
imgpro-0.0.1.dist-info/METADATA
imgpro-0.0.1.dist-info/WHEEL
imgpro-0.0.1.dist-info/top_level.txt
imgpro-0.0.1.dist-info/RECORD
