Metadata-Version: 2.1
Name: imgpro
Version: 0.0.1
Summary: Image processing tool package
Home-page: https://github.com/nanipumpkin/imgpro-pkg
Author: naniavalone
Author-email: marianne.avalone@gmail.com
License: UNKNOWN
Platform: UNKNOWN
Requires-Python: >=3.9
Requires-Dist: matplotlib (==3.6.1)
Requires-Dist: numpy (==1.23.4)
Requires-Dist: scikit-image (==0.19.3)
